Workbook

Sheet Dashboard
A1: Revenue Cycle Visibility Tracker
A2: Created by Kori Pickle | Simulated Data Only | No PHI
A4: Total Claims Tracked | C4: Denial Rate | E4: Clean Claim Rate | G4: Average Days in A/R
A5: =COUNTA('Claim Tracker'!A2:A1000) -> 15 | C5: =COUNTIF('Claim Tracker'!E2:E1000,"Denied")/COUNTA('Claim Tracker'!A2:A1000) -> 0.33333333 | E5: =COUNTIF('Claim Tracker'!F2:F1000,"Clean Claim")/COUNTA('Claim Tracker'!A2:A1000) -> 0.2 | G5: =AVERAGE('Claim Tracker'!K2:K1000) -> 20.2
A7: High-Risk Accounts | C7: Authorization Denials | E7: Eligibility Denials | G7: Rework Volume
A8: =COUNTIF('Claim Tracker'!L2:L1000,"Tier 1") -> 7 | C8: =COUNTIFS('Claim Tracker'!E2:E1000,"Denied",'Claim Tracker'!F2:F1000,"Authorization") -> 2 | E8: =COUNTIFS('Claim Tracker'!E2:E1000,"Denied",'Claim Tracker'!F2:F1000,"Eligibility") -> 2 | G8: =COUNTIF('Claim Tracker'!E2:E1000,"Denied")+COUNTIF('Claim Tracker'!E2:E1000,"Rejected") -> 7
A10: Root Cause Category | B10: Claim Count | C10: Denial Count | E10: Priority Tier | F10: Claim Count | G10: Total Amount
A11: Authorization | B11: =COUNTIF('Claim Tracker'!F2:F1000,A11) -> 3 | C11: =COUNTIFS('Claim Tracker'!F2:F1000,A11,'Claim Tracker'!E2:E1000,"Denied") -> 2 | E11: Tier 1 | F11: =COUNTIF('Claim Tracker'!L2:L1000,E11) -> 7 | G11: =SUMIF('Claim Tracker'!L2:L1000,E11,'Claim Tracker'!D2:D1000) -> 8425
A12: Eligibility | B12: =COUNTIF('Claim Tracker'!F2:F1000,A12) -> 3 | C12: =COUNTIFS('Claim Tracker'!F2:F1000,A12,'Claim Tracker'!E2:E1000,"Denied") -> 2 | E12: Tier 2 | F12: =COUNTIF('Claim Tracker'!L2:L1000,E12) -> 5 | G12: =SUMIF('Claim Tracker'!L2:L1000,E12,'Claim Tracker'!D2:D1000) -> 2770
A13: Documentation | B13: =COUNTIF('Claim Tracker'!F2:F1000,A13) -> 2 | C13: =COUNTIFS('Claim Tracker'!F2:F1000,A13,'Claim Tracker'!E2:E1000,"Denied") -> 1 | E13: Tier 3 | F13: =COUNTIF('Claim Tracker'!L2:L1000,E13) -> 3 | G13: =SUMIF('Claim Tracker'!L2:L1000,E13,'Claim Tracker'!D2:D1000) -> 1815
A14: Coding | B14: =COUNTIF('Claim Tracker'!F2:F1000,A14) -> 1 | C14: =COUNTIFS('Claim Tracker'!F2:F1000,A14,'Claim Tracker'!E2:E1000,"Denied") -> 0
A15: Payer/Data Error | B15: =COUNTIF('Claim Tracker'!F2:F1000,A15) -> 1 | C15: =COUNTIFS('Claim Tracker'!F2:F1000,A15,'Claim Tracker'!E2:E1000,"Denied") -> 0
A16: Payer Delay | B16: =COUNTIF('Claim Tracker'!F2:F1000,A16) -> 2 | C16: =COUNTIFS('Claim Tracker'!F2:F1000,A16,'Claim Tracker'!E2:E1000,"Denied") -> 0
A17: Clean Claim | B17: =COUNTIF('Claim Tracker'!F2:F1000,A17) -> 3 | C17: =COUNTIFS('Claim Tracker'!F2:F1000,A17,'Claim Tracker'!E2:E1000,"Denied") -> 0

Sheet Claim Tracker
A1: Claim ID | B1: Service Date | C1: Payer | D1: Claim Amount | E1: Current Status | F1: Root Cause Category | G1: Workflow Source | H1: Owner | I1: Next Action | J1: Due Date | K1: Days in A/R | L1: Priority Tier | M1: Notes
A2: CLM-1001 | B2: 46143 | C2: BlueCross | D2: 1250 | E2: Denied | F2: Eligibility | G2: Patient Access | H2: Registration Lead | I2: Verify active coverage and resubmit | J2: 46150 | K2: 18 | L2: Tier 1 | M2: High-dollar eligibility denial
A3: CLM-1002 | B3: 46144 | C3: Aetna | D3: 740 | E3: Pending | F3: Authorization | G3: Prior Authorization | H3: Auth Specialist | I3: Confirm approval number/date range | J3: 46149 | K3: 14 | L3: Tier 1 | M3: Service occurred near auth window
A4: CLM-1003 | B4: 46145 | C4: UnitedHealthcare | D4: 430 | E4: Paid | F4: Clean Claim | G4: Billing | H4: Billing Analyst | I4: No action needed | J4: 46145 | K4: 8 | L4: Tier 3 | M4: Clean payment
A5: CLM-1004 | B5: 46146 | C5: Cigna | D5: 980 | E5: Rejected | F5: Payer/Data Error | G5: Registration | H5: Patient Access Rep | I5: Correct member ID and rebill | J5: 46149 | K5: 11 | L5: Tier 2 | M5: Demographic mismatch
A6: CLM-1005 | B6: 46147 | C6: Medicare | D6: 1800 | E6: Denied | F6: Documentation | G6: Clinical Documentation | H6: Documentation Owner | I6: Request missing documentation | J6: 46149 | K6: 27 | L6: Tier 1 | M6: Medical necessity support missing
A7: CLM-1006 | B7: 46148 | C7: Medicaid | D7: 325 | E7: Pending | F7: Payer Delay | G7: A/R Follow-Up | H7: A/R Analyst | I7: Follow payer status | J7: 46154 | K7: 21 | L7: Tier 2 | M7: Payer processing delay
A8: CLM-1007 | B8: 46149 | C8: Humana | D8: 650 | E8: Denied | F8: Authorization | G8: Prior Authorization | H8: Auth Specialist | I8: Appeal with auth evidence | J8: 46153 | K8: 34 | L8: Tier 1 | M8: Authorization not matched
A9: CLM-1008 | B9: 46150 | C9: BlueCross | D9: 510 | E9: Paid | F9: Clean Claim | G9: Billing | H9: Billing Analyst | I9: No action needed | J9: 46150 | K9: 6 | L9: Tier 3 | M9: Paid first pass
A10: CLM-1009 | B10: 46151 | C10: Aetna | D10: 1120 | E10: Pending | F10: Eligibility | G10: Patient Access | H10: Registration Lead | I10: Review COB and coverage | J10: 46159 | K10: 19 | L10: Tier 1 | M10: COB unresolved
A11: CLM-1010 | B11: 46152 | C11: UnitedHealthcare | D11: 290 | E11: Rejected | F11: Coding | G11: Coding | H11: Coder | I11: Review diagnosis/procedure alignment | J11: 46154 | K11: 12 | L11: Tier 2 | M11: Coding edit
A12: CLM-1011 | B12: 46153 | C12: Cigna | D12: 1540 | E12: Denied | F12: Authorization | G12: Prior Authorization | H12: Auth Specialist | I12: Escalate missing auth denial | J12: 46154 | K12: 44 | L12: Tier 1 | M12: Timely follow-up needed
A13: CLM-1012 | B13: 46154 | C13: Medicare | D13: 875 | E13: Paid | F13: Clean Claim | G13: Billing | H13: Billing Analyst | I13: No action needed | J13: 46154 | K13: 9 | L13: Tier 3 | M13: Paid
... A16: CLM-1015 | B16: 46157 | C16: BlueCross | D16: 715 | E16: Pending | F16: Payer Delay | G16: A/R Follow-Up | H16: A/R Analyst | I16: Follow up by phone/portal | J16: 46163 | K16: 17 | L16: Tier 2 | M16: Waiting payer response

Sheet Denial Root Causes
A1: Root Cause Category | B1: Workflow Source | C1: Example Failure | D1: Downstream Risk | E1: Prevention Action | F1: Metric to Track
A2: Eligibility | B2: Patient Access | C2: Inactive coverage or wrong plan selected | D2: Coverage denial, rejection, patient billing confusion | E2: Verify active coverage and payer plan before service | F2: Eligibility-related denial rate
A3: Authorization | B3: Prior Authorization | C3: Requirement missed or approval details missing | D3: Missing authorization denial, delayed reimbursement | E3: Check payer rules and verify approval number/date range | F3: Authorization-related denial rate
A4: Documentation | B4: Clinical Documentation | C4: Missing medical necessity support | D4: Medical necessity denial or rework | E4: Use documentation readiness checklist | F4: Documentation-related denial rate
A5: Coding | B5: Coding | C5: Diagnosis/procedure mismatch | D5: Coding denial or claim edit | E5: Validate coding against documentation | F5: Coding-related denial rate
A6: Payer/Data Error | B6: Registration/Billing | C6: Wrong member ID or payer formatting issue | D6: Claim rejection or reroute delay | E6: Validate payer/member data before claim submission | F6: Claim rejection volume
A7: Payer Delay | B7: A/R Follow-Up | C7: No internal defect but payer response pending | D7: A/R aging and delayed cash flow | E7: Track payer-cycle pending separately | F7: Days in A/R

Sheet Workqueue Priority
A1: Priority Tier | B1: Criteria | C1: Example Claim Type | D1: Required Action | E1: Escalation Trigger
A2: Tier 1 | B2: High-dollar, denied, near timely filing risk, or >30 days in A/R | C2: Authorization denial, eligibility denial, high balance account | D2: Assign owner, next action, deadline, and escalation path | E2: No action within 48 hours or service/rebill deadline approaching
A3: Tier 2 | B3: Medium-dollar, pending payer response, documentation/coding rework, or 15–30 days in A/R | C3: Pending documentation, payer follow-up, coding edit | D3: Track status and follow-up date; resolve internal defect | E3: No update by due date or claim ages into Tier 1
A4: Tier 3 | B4: Paid, low-dollar, routine follow-up, or clean claim monitoring | C4: Paid clean claim or low-risk pending item | D4: Monitor and close when resolved | E4: Unexpected denial or aging trend appears

Sheet Metric Definitions
A1: Metric | B1: Definition | C1: Formula | D1: Why It Matters | E1: Owner | F1: Target Direction
A2: Total Claims Tracked | B2: Total simulated claims in the tracker | C2: =Dashboard!A5 -> 15 | D2: Shows tracker volume | E2: RCM Analyst | F2: Monitor volume
A3: Denial Rate | B3: Denied claims divided by all tracked claims | C3: =Dashboard!C5 -> 0.33333333 | D3: Shows denial burden and workflow risk | E3: RCM Analyst | F3: Lower
A4: Clean Claim Rate | B4: Paid clean claims divided by all tracked claims | C4: =Dashboard!E5 -> 0.2 | D4: Shows first-pass readiness | E4: Billing Lead | F4: Higher
A5: Average Days in A/R | B5: Average days in A/R across tracked claims | C5: =Dashboard!G5 -> 20.2 | D5: Shows reimbursement delay | E5: A/R Lead | F5: Lower
A6: High-Risk Accounts | B6: Tier 1 claims count | C6: =Dashboard!A8 -> 7 | D6: Shows urgent follow-up workload | E6: RCM Analyst | F6: Lower
A7: Authorization Denials | B7: Denied claims tagged Authorization | C7: =Dashboard!C8 -> 2 | D7: Shows prior auth workflow risk | E7: Auth Specialist | F7: Lower
A8: Eligibility Denials | B8: Denied claims tagged Eligibility | C8: =Dashboard!E8 -> 2 | D8: Shows front-end verification risk | E8: Patient Access Lead | F8: Lower
A9: Rework Volume | B9: Claims denied or rejected requiring action | C9: =Dashboard!G8 -> 7 | D9: Shows avoidable staff workload | E9: Operations Lead | F9: Lower
